{
"life" : 
{
    "name": "life",
    "max":"life_max",
    "description":"increase life",
    "link":"img/game/heal.png",
    "price": 40,
    "amont": 3
},
"ammo" : 
{
    "name": "weapon_bullet",
    "max": "weapon_bullet_max",
    "description":"incr ammo",
    "link":"img/game/iammo.webp",
    "price": 10,
    "amont": 100
},

"basic_turret":
{
    "name": "turret",
    "description":"makeshift turret",
    "link":"img/game/velocity.png",
    "iglink":"img/game/basic_turret.png",
    "damage":1,
    "weapon_bullet":10,
    "range":200,
    "price": 1,
    "amont": 1
},
"auto_turret_2":
{
    "name": "turret",
    "description":"basic turret",
    "link":"img/game/velocity.png",
    "iglink":"img/game/2_turret.png",
    "damage":1,
    "weapon_bullet":20,
    "range":250,
    "price": 2,
    "amont": 1
}
}